{"1":{"audioUrl":"https://audio-cdn.tarteel.ai/quran/minshawyMurattal/091001.mp3","durationMs":2800,"segments":[[1,0,1320],[2,1520,2800]]},"2":{"audioUrl":"https://audio-cdn.tarteel.ai/quran/minshawyMurattal/091002.mp3","durationMs":3520,"segments":[[1,800,1480],[2,1960,2160],[3,2520,3520]]},"3":{"audioUrl":"https://audio-cdn.tarteel.ai/quran/minshawyMurattal/091003.mp3","durationMs":4480,"segments":[[1,0,2120],[2,2720,2920],[3,3240,4480]]},"4":{"audioUrl":"https://audio-cdn.tarteel.ai/quran/minshawyMurattal/091004.mp3","durationMs":3720,"segments":[[1,0,1280],[2,1880,2040],[3,2400,3720]]},"5":{"audioUrl":"https://audio-cdn.tarteel.ai/quran/minshawyMurattal/091005.mp3","durationMs":5240,"segments":[[1,0,3120],[2,3330,3430],[3,4240,5240]]},"6":{"audioUrl":"https://audio-cdn.tarteel.ai/quran/minshawyMurattal/091006.mp3","durationMs":3600,"segments":[[1,0,1400],[2,1650,1750],[3,2520,3600]]},"7":{"audioUrl":"https://audio-cdn.tarteel.ai/quran/minshawyMurattal/091007.mp3","durationMs":4080,"segments":[[1,0,960],[2,1770,1870],[3,2680,4080]]},"8":{"audioUrl":"https://audio-cdn.tarteel.ai/quran/minshawyMurattal/091008.mp3","durationMs":5840,"segments":[[1,0,1600],[2,2000,3520],[3,4040,5840]]},"9":{"audioUrl":"https://audio-cdn.tarteel.ai/quran/minshawyMurattal/091009.mp3","durationMs":4280,"segments":[[1,0,70],[2,720,1720],[3,1930,2030],[4,2800,4280]]},"10":{"audioUrl":"https://audio-cdn.tarteel.ai/quran/minshawyMurattal/091010.mp3","durationMs":4160,"segments":[[1,0,400],[2,880,1600],[3,1790,1890],[4,2760,4160]]},"11":{"audioUrl":"https://audio-cdn.tarteel.ai/quran/minshawyMurattal/091011.mp3","durationMs":4560,"segments":[[1,0,1400],[2,2480,2680],[3,2880,4560]]},"12":{"audioUrl":"https://audio-cdn.tarteel.ai/quran/minshawyMurattal/091012.mp3","durationMs":3920,"segments":[[1,0,720],[2,1000,2440],[3,2680,3920]]},"13":{"audioUrl":"https://audio-cdn.tarteel.ai/quran/minshawyMurattal/091013.mp3","durationMs":8800,"segments":[[1,0,1160],[2,1570,1670],[3,2560,3240],[4,3640,4360],[5,4520,5680],[6,6120,6800],[7,7120,8800]]},"14":{"audioUrl":"https://audio-cdn.tarteel.ai/quran/minshawyMurattal/091014.mp3","durationMs":13480,"segments":[[1,0,1880],[2,2200,3680],[3,4200,5600],[4,6160,6680],[5,7920,8320],[6,9360,11600],[7,11680,13480]]},"15":{"audioUrl":"https://audio-cdn.tarteel.ai/quran/minshawyMurattal/091015.mp3","durationMs":4040,"segments":[[1,0,70],[2,1320,1760],[3,2680,4040]]}}