{"1":{"audioUrl":"https://audio-cdn.tarteel.ai/quran/husaryMuallim/101001.mp3","durationMs":4160,"segments":[[1,680,4160]]},"2":{"audioUrl":"https://audio-cdn.tarteel.ai/quran/husaryMuallim/101002.mp3","durationMs":4160,"segments":[[1,0,70],[2,840,4160]]},"3":{"audioUrl":"https://audio-cdn.tarteel.ai/quran/husaryMuallim/101003.mp3","durationMs":8800,"segments":[[1,0,70],[2,2520,3400],[3,3750,3850],[4,4360,8800]]},"4":{"audioUrl":"https://audio-cdn.tarteel.ai/quran/husaryMuallim/101004.mp3","durationMs":10640,"segments":[[1,0,70],[2,1520,2200],[3,2920,3640],[4,3920,5640],[5,6120,10640]]},"5":{"audioUrl":"https://audio-cdn.tarteel.ai/quran/husaryMuallim/101005.mp3","durationMs":9440,"segments":[[1,0,1320],[2,1760,2760],[3,3040,4320],[4,4640,9440]]},"6":{"audioUrl":"https://audio-cdn.tarteel.ai/quran/husaryMuallim/101006.mp3","durationMs":8440,"segments":[[1,0,1240],[2,1790,1890],[3,2640,3960],[4,4200,8440]]},"7":{"audioUrl":"https://audio-cdn.tarteel.ai/quran/husaryMuallim/101007.mp3","durationMs":8440,"segments":[[1,0,720],[2,930,1030],[3,1520,2680],[4,3280,8440]]},"8":{"audioUrl":"https://audio-cdn.tarteel.ai/quran/husaryMuallim/101008.mp3","durationMs":7840,"segments":[[1,0,1280],[2,1810,1910],[3,2520,3680],[4,3920,7840]]},"9":{"audioUrl":"https://audio-cdn.tarteel.ai/quran/husaryMuallim/101009.mp3","durationMs":5840,"segments":[[1,0,1600],[2,2000,5840]]},"10":{"audioUrl":"https://audio-cdn.tarteel.ai/quran/husaryMuallim/101010.mp3","durationMs":7320,"segments":[[1,0,70],[2,2400,3320],[3,3650,3750],[4,4280,7320]]},"11":{"audioUrl":"https://audio-cdn.tarteel.ai/quran/husaryMuallim/101011.mp3","durationMs":7120,"segments":[[1,0,1120],[2,1720,7120]]}}